streamstory/entities.py
streamstory/model.py
streamstory-0.0.4.dist-info/METADATA
streamstory-0.0.4.dist-info/WHEEL
streamstory-0.0.4.dist-info/RECORD
