Metadata-Version: 2.4
Name: streamstory
Version: 0.0.4
Summary: StreamStory Python Client
Requires-Python: >=3.10
Requires-Dist: dacite>=1.8.1
Requires-Dist: numpy>=1.26.4
Requires-Dist: pandas>=2.2.2
Requires-Dist: pydantic>=2.8.2
Requires-Dist: python-dotenv>=1.0.1
Requires-Dist: requests>=2.32.3
